BuildBinary.py
PythonProjectBootstrapperTesting/EntryPoint.py
PythonProjectBootstrapperTesting/Math.py
PythonProjectBootstrapperTesting/__init__.py
PythonProjectBootstrapperTesting-0.1.4.dist-info/LICENSE.txt
PythonProjectBootstrapperTesting-0.1.4.dist-info/METADATA
PythonProjectBootstrapperTesting-0.1.4.dist-info/WHEEL
PythonProjectBootstrapperTesting-0.1.4.dist-info/entry_points.txt
PythonProjectBootstrapperTesting-0.1.4.dist-info/top_level.txt
PythonProjectBootstrapperTesting-0.1.4.dist-info/RECORD
