Metadata-Version: 2.1
Name: PythonProjectBootstrapperTesting
Version: 0.1.4
Summary: Python project bootstrapper test output
Author-email: Varun Narayan <varun646@gmail.com>
License: MIT
Project-URL: Homepage, https://github.com/varun646/PythonProjectBootstrapperTest
Project-URL: Documentation, https://github.com/varun646/PythonProjectBootstrapperTest
Project-URL: Repository, https://github.com/varun646/PythonProjectBootstrapperTest
Classifier: License :: OSI Approved :: MIT License
Classifier: Operating System :: MacOS
Classifier: Operating System :: Microsoft :: Windows
Classifier: Operating System :: POSIX :: Linux
Classifier: Programming Language :: Python
Classifier: Programming Language :: Python :: 3.10
Classifier: Programming Language :: Python :: 3.11
Classifier: Programming Language :: Python :: 3.12
License-File: LICENSE.txt
Requires-Dist: typer ~=0.9
Provides-Extra: dev
Requires-Dist: dbrownell-DevTools ; extra == 'dev'
Provides-Extra: package
Requires-Dist: build ==1.* ; extra == 'package'
Requires-Dist: cx-Freeze ==6.* ; extra == 'package'
Requires-Dist: twine ==4.* ; extra == 'package'
